CHANGELOG.md
README.md
fastapi_telegram_auth/__init__.py
fastapi_telegram_auth/auth.py
fastapi_telegram_auth/types.py
fastapi_telegram_auth/utils.py
fastapi_telegram_auth-0.3.0.dist-info/LICENSE
fastapi_telegram_auth-0.3.0.dist-info/METADATA
fastapi_telegram_auth-0.3.0.dist-info/WHEEL
fastapi_telegram_auth-0.3.0.dist-info/RECORD
