Metadata-Version: 2.1
Name: fastapi-telegram-auth
Version: 0.3.0
Summary: FastAPI router for fast Telegram auth integration
Home-page: https://github.com/pylakey/fastapi_telegram_auth
License: MIT
Author: pylakey
Author-email: pylakey@protonmail.com
Requires-Python: >=3.10,<4.0
Classifier: Framework :: AsyncIO
Classifier: License :: OSI Approved :: MIT License
Classifier: Operating System :: OS Independent
Classifier: Programming Language :: Python :: 3
Classifier: Programming Language :: Python :: 3.10
Classifier: Programming Language :: Python :: 3.11
Classifier: Topic :: Software Development :: Libraries :: Python Modules
Classifier: Typing :: Typed
Requires-Dist: fastapi (>=0.92.0,<=0.96.0)
Requires-Dist: pydantic (>=1.10.5,<2.0.0)
Project-URL: Repository, https://github.com/pylakey/fastapi_telegram_auth
